mude/__init__.py
mude/environment_checking.py
mude/week1/__init__.py
mude/week1/requirements.toml
MUDE-0.1.3.dist-info/LICENSE
MUDE-0.1.3.dist-info/METADATA
MUDE-0.1.3.dist-info/WHEEL
MUDE-0.1.3.dist-info/top_level.txt
MUDE-0.1.3.dist-info/RECORD
