Metadata-Version: 2.1
Name: MUDE
Version: 0.1.3
Summary: A Python package in support of the Modelling, Uncertainty, and Data Analysis for Engineers course given at TU Delft, Civil Engineering
Author-email: Robert Lanzafame <r.c.lanzafame@tudelft.nl>, Quinten van Woerkom <q.e.vanwoerkom@student.tudelft.nl>
Project-URL: Homepage, https://gitlab.tudelft.nl/mude/mude
Project-URL: Bug Tracker, https://gitlab.tudelft.nl/mude/mude/-/issues
Requires-Python: >=3.11
License-File: LICENSE
Requires-Dist: setuptools >=61.0
